README.md
setup.py
directdm/__init__.py
directdm/_version.py
directdm/dm_eft.py
directdm/wilson_coefficients.py
directdm.egg-info/PKG-INFO
directdm.egg-info/SOURCES.txt
directdm.egg-info/dependency_links.txt
directdm.egg-info/requires.txt
directdm.egg-info/top_level.txt
directdm/match/__init__.py
directdm/match/dim4_gauge_contribution.py
directdm/num/__init__.py
directdm/num/num_input.py
directdm/num/single_nucleon_form_factors.py
directdm/run/__init__.py
directdm/run/adm.py
directdm/run/full_adm_g1.py
directdm/run/full_adm_g2.py
directdm/run/full_adm_yb.py
directdm/run/full_adm_yc.py
directdm/run/full_adm_yt.py
directdm/run/full_adm_ytau.py
directdm/run/rge.py