Metadata-Version: 1.0
Name: directdm
Version: 2.1.3
Summary: A python package for dark matter direct detection
Home-page: https://directdm.github.io
Author: Fady Bishara, Joachim Brod, Benjamin Grinstein, Jure Zupan
Author-email: joachim.brod@uc.edu
License: MIT
Platform: UNKNOWN
